gradescrape/__init__.py
gradescrape/assignment.py
gradescrape/course.py
gradescrape/login.py
gradescrape/session.py
gradescrape/util.py
gradescrape-0.0.1.post1.dist-info/LICENSE
gradescrape-0.0.1.post1.dist-info/METADATA
gradescrape-0.0.1.post1.dist-info/WHEEL
gradescrape-0.0.1.post1.dist-info/top_level.txt
gradescrape-0.0.1.post1.dist-info/RECORD
